nnpf/__init__.py
nnpf/__main__.py
nnpf/cmd/__init__.py
nnpf/cmd/bench.py
nnpf/cmd/infos.py
nnpf/cmd/selftest.py
nnpf/cmd/train.py
nnpf/datasets/__init__.py
nnpf/datasets/phase_field.py
nnpf/domain/__init__.py
nnpf/domain/domain.py
nnpf/fft/__init__.py
nnpf/fft/domain.py
nnpf/fft/toolbox.py
nnpf/functional/__init__.py
nnpf/functional/heat.py
nnpf/functional/norms.py
nnpf/functional/operators.py
nnpf/functional/phase_field.py
nnpf/functional/utils.py
nnpf/io/__init__.py
nnpf/io/tensorboard.py
nnpf/io/vtk.py
nnpf/models/__init__.py
nnpf/models/allen_cahn_splitting.py
nnpf/models/heat_array.py
nnpf/models/reaction.py
nnpf/nn/__init__.py
nnpf/nn/conv.py
nnpf/nn/models.py
nnpf/nn/utils.py
nnpf/problems/__init__.py
nnpf/problems/problem.py
nnpf/problems/allen_cahn/__init__.py
nnpf/problems/allen_cahn/datasets.py
nnpf/problems/allen_cahn/problem.py
nnpf/problems/allen_cahn/utils.py
nnpf/problems/heat/__init__.py
nnpf/problems/heat/datasets.py
nnpf/problems/heat/problem.py
nnpf/problems/heat/solution.py
nnpf/problems/mean_curvature/__init__.py
nnpf/problems/mean_curvature/datasets.py
nnpf/problems/mean_curvature/problem.py
nnpf/problems/mean_curvature/utils.py
nnpf/problems/reaction/__init__.py
nnpf/problems/reaction/datasets.py
nnpf/problems/reaction/problem.py
nnpf/problems/reaction/solution.py
nnpf/problems/steiner/__init__.py
nnpf/problems/steiner/datasets.py
nnpf/problems/steiner/problem.py
nnpf/problems/steiner/utils.py
nnpf/problems/willmore/__init__.py
nnpf/problems/willmore/datasets.py
nnpf/problems/willmore/problem.py
nnpf/problems/willmore/utils.py
nnpf/shapes/__init__.py
nnpf/shapes/operators.py
nnpf/shapes/shapes.py
nnpf/shapes/slices.py
nnpf/shapes/utils.py
nnpf/trainer/__init__.py
nnpf/trainer/trainer.py
nnpf/utils/__init__.py
nnpf/utils/inspect.py
nnpf/utils/path.py
nnpf/visu/__init__.py
nnpf/visu/visu.py
nnpf-1.0.2.dist-info/LICENSE.md
nnpf-1.0.2.dist-info/METADATA
nnpf-1.0.2.dist-info/WHEEL
nnpf-1.0.2.dist-info/entry_points.txt
nnpf-1.0.2.dist-info/top_level.txt
nnpf-1.0.2.dist-info/RECORD
