Metadata-Version: 2.1
Name: nnpf
Version: 1.0.2
Summary: Neural Network for Phase-Field models
Author-email: Roland Denis <denis@math.univ-lyon1.fr>, Garry Terii <terii@math.univ-lyon1.fr>
Maintainer-email: Roland Denis <denis@math.univ-lyon1.fr>
Project-URL: homepage, https://github.com/PhaseFieldICJ/nnpf
Project-URL: repository, https://github.com/PhaseFieldICJ/nnpf
Project-URL: Bug Tracker, https://github.com/PhaseFieldICJ/nnpf/issues
Keywords: phase field,mean curvature,neural network
Classifier: Development Status :: 5 - Production/Stable
Classifier: Programming Language :: Python :: 3
Classifier: Operating System :: OS Independent
Classifier: License :: OSI Approved :: MIT License
Classifier: Intended Audience :: Science/Research
Classifier: Topic :: Scientific/Engineering :: Mathematics
Classifier: Topic :: Scientific/Engineering :: Artificial Intelligence
Requires-Python: >=3.8
License-File: LICENSE.md
Requires-Dist: numpy<2
Requires-Dist: matplotlib
Requires-Dist: torch<=1.12.1,>=1.10.0
Requires-Dist: torchvision>=0.8.1
Requires-Dist: torchmetrics<0.8.0
Requires-Dist: pytorch-lightning==1.4.5
Requires-Dist: tensorboard<2.12
Requires-Dist: tqdm
Requires-Dist: imageio
Requires-Dist: imageio-ffmpeg
Requires-Dist: torchinfo
Requires-Dist: pytest
